prompt_toolkit/__init__.py
prompt_toolkit/auto_suggest.py
prompt_toolkit/buffer.py
prompt_toolkit/cache.py
prompt_toolkit/cursor_shapes.py
prompt_toolkit/data_structures.py
prompt_toolkit/document.py
prompt_toolkit/enums.py
prompt_toolkit/history.py
prompt_toolkit/keys.py
prompt_toolkit/log.py
prompt_toolkit/mouse_events.py
prompt_toolkit/patch_stdout.py
prompt_toolkit/py.typed
prompt_toolkit/renderer.py
prompt_toolkit/search.py
prompt_toolkit/selection.py
prompt_toolkit/token.py
prompt_toolkit/utils.py
prompt_toolkit/validation.py
prompt_toolkit/win32_types.py
prompt_toolkit/application/__init__.py
prompt_toolkit/application/application.py
prompt_toolkit/application/current.py
prompt_toolkit/application/dummy.py
prompt_toolkit/application/run_in_terminal.py
prompt_toolkit/clipboard/__init__.py
prompt_toolkit/clipboard/base.py
prompt_toolkit/clipboard/in_memory.py
prompt_toolkit/clipboard/pyperclip.py
prompt_toolkit/completion/__init__.py
prompt_toolkit/completion/base.py
prompt_toolkit/completion/deduplicate.py
prompt_toolkit/completion/filesystem.py
prompt_toolkit/completion/fuzzy_completer.py
prompt_toolkit/completion/nested.py
prompt_toolkit/completion/word_completer.py
prompt_toolkit/contrib/__init__.py
prompt_toolkit/contrib/completers/__init__.py
prompt_toolkit/contrib/completers/system.py
prompt_toolkit/contrib/regular_languages/__init__.py
prompt_toolkit/contrib/regular_languages/compiler.py
prompt_toolkit/contrib/regular_languages/completion.py
prompt_toolkit/contrib/regular_languages/lexer.py
prompt_toolkit/contrib/regular_languages/regex_parser.py
prompt_toolkit/contrib/regular_languages/validation.py
prompt_toolkit/contrib/ssh/__init__.py
prompt_toolkit/contrib/ssh/server.py
prompt_toolkit/contrib/telnet/__init__.py
prompt_toolkit/contrib/telnet/log.py
prompt_toolkit/contrib/telnet/protocol.py
prompt_toolkit/contrib/telnet/server.py
prompt_toolkit/eventloop/__init__.py
prompt_toolkit/eventloop/async_generator.py
prompt_toolkit/eventloop/inputhook.py
prompt_toolkit_dim-3.0.53.dist-info/licenses/AUTHORS.rst
prompt_toolkit_dim-3.0.53.dist-info/licenses/LICENSE
prompt_toolkit_dim-3.0.53.dist-info/METADATA
prompt_toolkit_dim-3.0.53.dist-info/WHEEL
prompt_toolkit_dim-3.0.53.dist-info/top_level.txt
prompt_toolkit_dim-3.0.53.dist-info/RECORD
